thinkedgecan.py
thinkedgecan-0.1.2.dist-info/entry_points.txt
thinkedgecan-0.1.2.dist-info/WHEEL
thinkedgecan-0.1.2.dist-info/METADATA
thinkedgecan-0.1.2.dist-info/RECORD
