Metadata-Version: 2.1
Name: thinkedgecan
Version: 0.1.2
Summary: Interface between the SUNIX SDC Expansion Board Software and python-can
Keywords: CAN,can-bus,python-can,sunix
Author-email: Lukas Schreiber <lukas.schreiber@ifos-gmbh.de>
Requires-Python: >=3.8
Requires-Dist: python-can >= 4.0.0, < 5
